link_notify/__init__.py
link_notify/link_notify.py
link_notify-0.2.dist-info/LICENSE
link_notify-0.2.dist-info/METADATA
link_notify-0.2.dist-info/WHEEL
link_notify-0.2.dist-info/top_level.txt
link_notify-0.2.dist-info/RECORD
