Metadata-Version: 2.1
Name: link-notify
Version: 0.2
Summary: Creates notification with button
Author: Prog Bits
Author-email: progbitsprojects@gmail.com
License: UNKNOWN
Keywords: python,notification,notification with buttons,create notifications,notification with links
Platform: UNKNOWN
Classifier: Development Status :: 1 - Planning
Classifier: Intended Audience :: Developers
Classifier: Programming Language :: Python :: 3
Classifier: Operating System :: Unix
Classifier: Operating System :: MacOS :: MacOS X
Classifier: Operating System :: Microsoft :: Windows
License-File: LICENSE
Requires-Dist: ctypes
Requires-Dist: webbrowser
